unfolded/demo/__init__.py
unfolded.demo-0.0.1.dist-info/WHEEL
unfolded.demo-0.0.1.dist-info/METADATA
unfolded.demo-0.0.1.dist-info/RECORD
