Metadata-Version: 2.1
Name: unfolded.demo
Version: 0.0.1
Summary: Public stub for the private unfolded.demo package
License: (c) 2022 Foursquare Labs, Inc. Terms available at https://www.unfolded.ai/terms-of-service/
Author: Unfolded
Author-email: contact@unfolded.ai
Requires-Python: >=3.6,<4.0
Classifier: License :: Other/Proprietary License
Classifier: Programming Language :: Python :: 3
Classifier: Programming Language :: Python :: 3.6
Classifier: Programming Language :: Python :: 3.7
Classifier: Programming Language :: Python :: 3.8
Classifier: Programming Language :: Python :: 3.9
